natural_language_geocoding/__init__.py
natural_language_geocoding/errors.py
natural_language_geocoding/main.py
natural_language_geocoding/models.py
natural_language_geocoding/natural_earth.py
natural_language_geocoding/place_lookup.py
natural_language_geocoding/prompt.md
natural_language_geocoding/prompt.py
natural_language_geocoding/py.typed
natural_language_geocoding/splitter.py
natural_language_geocoding/eval/__init__.py
natural_language_geocoding/eval/evaluation_analysis.py
natural_language_geocoding/eval/evaluation_core.py
natural_language_geocoding/eval/evaluator.py
natural_language_geocoding/eval/tree_distance.py
natural_language_geocoding/eval/templates/full_eval_result.md
natural_language_geocoding/eval/templates/single_eval_diff_result.md
natural_language_geocoding/eval/templates/single_eval_success_result.md
natural_language_geocoding/geocode_index/__init__.py
natural_language_geocoding/geocode_index/geocode_index_place_lookup.py
natural_language_geocoding/geocode_index/geoplace.py
natural_language_geocoding/geocode_index/hierachical_place_cache.py
natural_language_geocoding/geocode_index/index.py
natural_language_geocoding/geocode_index/opensearch_utils.py
natural_language_geocoding/geocode_index/ingesters/__init__.py
natural_language_geocoding/geocode_index/ingesters/hierarchy_finder.py
natural_language_geocoding/geocode_index/ingesters/ingest_utils.py
natural_language_geocoding/geocode_index/ingesters/natural_earth.py
natural_language_geocoding/geocode_index/ingesters/whos_on_first.py
natural_language_geocoding/geocode_index/ingesters/composed_places/__init__.py
natural_language_geocoding/geocode_index/ingesters/composed_places/composers_core.py
natural_language_geocoding/geocode_index/ingesters/composed_places/iberian_peninsula.py
natural_language_geocoding/geocode_index/ingesters/composed_places/ingest.py
natural_language_geocoding/tests/__init__.py
natural_language_geocoding/tests/canned_place_lookup.py
natural_language_geocoding-0.1.2.dist-info/licenses/LICENSE
natural_language_geocoding-0.1.2.dist-info/METADATA
natural_language_geocoding-0.1.2.dist-info/WHEEL
natural_language_geocoding-0.1.2.dist-info/entry_points.txt
natural_language_geocoding-0.1.2.dist-info/top_level.txt
natural_language_geocoding-0.1.2.dist-info/RECORD
