Metadata-Version: 2.4
Name: natural-language-geocoding
Version: 0.1.2
Summary: Natural Language Geocoding implements an AI technique to convert natural language descriptions of spatial areas into polygons.
Author-email: Jason Gilman <jason@element84.com>
Maintainer-email: Jason Gilman <jason@element84.com>
License:                                  Apache License
Project-URL: Github, https://github.com/Element84/natural-language-geocoding
Requires-Python: >=3.12
License-File: LICENSE
Requires-Dist: requests>=2.32.3
Requires-Dist: e84-geoai-common>=0.0.7
Requires-Dist: tabulate
Requires-Dist: opensearch-py
Provides-Extra: demo
Requires-Dist: streamlit>=1.38.0; extra == "demo"
Requires-Dist: streamlit-folium>=0.22.1; extra == "demo"
Requires-Dist: watchdog>=6.0.0; extra == "demo"
Provides-Extra: eval
Requires-Dist: deepdiff>=8.6.1; extra == "eval"
Requires-Dist: zss; extra == "eval"
Provides-Extra: dev
Requires-Dist: pytest>=8.3.3; extra == "dev"
Requires-Dist: pytest-watch; extra == "dev"
Requires-Dist: ipykernel>=6.29.5; extra == "dev"
Requires-Dist: ruff>=0.6.8; extra == "dev"
Requires-Dist: pyright>=1.1.381; extra == "dev"
Requires-Dist: build>=1.2.2; extra == "dev"
Requires-Dist: pre-commit>=3.8.0; extra == "dev"
Requires-Dist: pre-commit-hooks>=4.6.0; extra == "dev"
Requires-Dist: rich; extra == "dev"
Dynamic: license-file
